<?xml version="1.0" encoding="UTF-8"?>
<list>
	<dungeon id="1" name="Solo Story Mode" players="1" rewards="6622,1;8762,3" rewardHtm="NULL">
		<stage order="1" loc="173192,-85688,-7216" teleport="true" minutes="5">
			<mob npcId="501" locs="173656,-86216,-7216;173704,-85736,-7216;173432,-85272,-7216;172808,-85528,-7216;172904,-86152,-7216"/>
		</stage>
		<stage order="2" loc="173192,-76554,-7219" teleport="true" minutes="3">
			<mob npcId="502" locs="173368,-77144,-7216;173592,-77128,-7216;173800,-76984,-7216;173800,-76600,-7216;173800,-76024,-7216;173160,-75928,-7216"/>
		</stage>
	</dungeon>
	<dungeon id="2" name="Quatro Hard Mode" players="4" rewards="6622,1;8762,3" rewardHtm="NULL">
		<stage order="1" loc="173192,-85688,-7216" teleport="true" minutes="5">
			<mob npcId="502" locs="173656,-86216,-7216;173704,-85736,-7216;173432,-85272,-7216;172808,-85528,-7216;172904,-86152,-7216"/>
		</stage>
		<stage order="2" loc="173192,-76554,-7219" teleport="true" minutes="3">
			<mob npcId="501" locs="173368,-77144,-7216;173592,-77128,-7216;173800,-76984,-7216;173800,-76600,-7216;173800,-76024,-7216;173160,-75928,-7216"/>
		</stage>
	</dungeon>
</list>